[
 {
 "code": "TS1110",
"nom": "Carthage ",
"value": 1.855e+05 
},
{
 "code": "TS1111",
"nom": "La Medina ",
"value": 2.4959e+05 
},
{
 "code": "TS1112",
"nom": "Bab El Bhar ",
"value": 2.4987e+05 
},
{
 "code": "TS1113",
"nom": "Bab Souika ",
"value": 2.4918e+05 
},
{
 "code": "TS1114",
"nom": "El Omrane ",
"value": 2.4708e+05 
},
{
 "code": "TS1115",
"nom": "El Omrane Supérieur ",
"value": 2.367e+05 
},
{
 "code": "TS1116",
"nom": "Ettahrir ",
"value": 2.3953e+05 
},
{
 "code": "TS1117",
"nom": "El Menzah ",
"value": 2.4367e+05 
},
{
 "code": "TS1118",
"nom": "Cité El Khadhra ",
"value": 2.4148e+05 
},
{
 "code": "TS1119",
"nom": "Le Bardo ",
"value": 2.415e+05 
},
{
 "code": "TS111A",
"nom": "Sijoumi ",
"value": 2.4835e+05 
},
{
 "code": "TS111B",
"nom": "Ezzouhour ",
"value": 2.4399e+05 
},
{
 "code": "TS111C",
"nom": "El Hrairia ",
"value": 2.1502e+05 
},
{
 "code": "TS111D",
"nom": "Sidi Hassine ",
"value": 2.2178e+05 
},
{
 "code": "TS111E",
"nom": "El Ouardia ",
"value": 2.4258e+05 
},
{
 "code": "TS111F",
"nom": "El Kabaria ",
"value": 2.358e+05 
},
{
 "code": "TS111G",
"nom": "Sidi El Béchir ",
"value": 2.4891e+05 
},
{
 "code": "TS111H",
"nom": "Djebel Djelloud ",
"value": 2.4032e+05 
},
{
 "code": "TS111I",
"nom": "La Goulette ",
"value": 2.0253e+05 
},
{
 "code": "TS111J",
"nom": "Le Kram ",
"value": 2.1483e+05 
},
{
 "code": "TS111K",
"nom": "La Marsa ",
"value": 1.7373e+05 
},
{
 "code": "TS1120",
"nom": "L Ariana Ville  ",
"value": 2.3306e+05 
},
{
 "code": "TS1121",
"nom": "Soukra ",
"value": 2.0808e+05 
},
{
 "code": "TS1122",
"nom": "Raoued ",
"value": 1.8323e+05 
},
{
 "code": "TS1123",
"nom": "Kalaât El Andalous ",
"value":  91018 
},
{
 "code": "TS1124",
"nom": "Sidi Thabet ",
"value": 1.4775e+05 
},
{
 "code": "TS1125",
"nom": "Cité Ettadhamen ",
"value": 2.238e+05 
},
{
 "code": "TS1126",
"nom": "El Mnihla ",
"value": 2.1433e+05 
},
{
 "code": "TS1130",
"nom": "Ben Arous  ",
"value": 2.2824e+05 
},
{
 "code": "TS1131",
"nom": "La Nouvelle Medina ",
"value": 2.1391e+05 
},
{
 "code": "TS1132",
"nom": "El Mourouj ",
"value": 2.2201e+05 
},
{
 "code": "TS1133",
"nom": "Hammam Lif ",
"value": 1.5304e+05 
},
{
 "code": "TS1134",
"nom": "Hammam Chôtt ",
"value": 1.1957e+05 
},
{
 "code": "TS1135",
"nom": "Bou Mhel El Bassatine ",
"value": 1.7404e+05 
},
{
 "code": "TS1136",
"nom": "Ezzahra ",
"value": 1.9313e+05 
},
{
 "code": "TS1137",
"nom": "Radès ",
"value": 2.1506e+05 
},
{
 "code": "TS1138",
"nom": "Megrine ",
"value": 2.3324e+05 
},
{
 "code": "TS1139",
"nom": "Mohamedia ",
"value": 1.3907e+05 
},
{
 "code": "TS113A",
"nom": "Fouchana ",
"value": 2.0698e+05 
},
{
 "code": "TS113B",
"nom": "Mornag ",
"value":  98369 
},
{
 "code": "TS1140",
"nom": "Mannouba  ",
"value": 2.085e+05 
},
{
 "code": "TS1141",
"nom": "Douar Hicher ",
"value": 2.032e+05 
},
{
 "code": "TS1142",
"nom": "Oued Ellil ",
"value": 1.5374e+05 
},
{
 "code": "TS1143",
"nom": "Mornaguia ",
"value":  86479 
},
{
 "code": "TS1144",
"nom": "Borj Amri ",
"value":  35831 
},
{
 "code": "TS1145",
"nom": "Djedeida ",
"value":  73750 
},
{
 "code": "TS1146",
"nom": "Tebourba ",
"value":  14695 
},
{
 "code": "TS1147",
"nom": "El Battane ",
"value":  18122 
},
{
 "code": "TS1150",
"nom": "Nabeul  ",
"value":  17873 
},
{
 "code": "TS1151",
"nom": "Dar Châabane El Fehri ",
"value":  18264 
},
{
 "code": "TS1152",
"nom": "Beni khiar ",
"value":  15286 
},
{
 "code": "TS1153",
"nom": "Korba ",
"value":  13519 
},
{
 "code": "TS1154",
"nom": "Menzel Temime ",
"value":   6905 
},
{
 "code": "TS1155",
"nom": "El Mida ",
"value": 9378.4 
},
{
 "code": "TS1156",
"nom": "Kelibia ",
"value": 5660.8 
},
{
 "code": "TS1157",
"nom": "Hammam El Guezaz ",
"value": 4909.9 
},
{
 "code": "TS1158",
"nom": "El Haouaria ",
"value": 4863.6 
},
{
 "code": "TS1159",
"nom": "Takelsa ",
"value": 8766.1 
},
{
 "code": "TS115A",
"nom": "Soliman ",
"value":  42624 
},
{
 "code": "TS115B",
"nom": "Menzel Bouzelfa ",
"value":  16796 
},
{
 "code": "TS115C",
"nom": "Beni Khalled ",
"value":  21267 
},
{
 "code": "TS115D",
"nom": "Grombalia ",
"value":  47737 
},
{
 "code": "TS115E",
"nom": "Bou Argoub ",
"value":  23321 
},
{
 "code": "TS115F",
"nom": "Hammamet ",
"value":  16206 
},
{
 "code": "TS1160",
"nom": "Zaghouan  ",
"value": 9552.3 
},
{
 "code": "TS1161",
"nom": "Ez-Zeriba ",
"value": 5549.1 
},
{
 "code": "TS1162",
"nom": "Bir Mchergua ",
"value":  18033 
},
{
 "code": "TS1163",
"nom": "El Fahs ",
"value": 2496.5 
},
{
 "code": "TS1164",
"nom": "En-Nadhour ",
"value": 2079.5 
},
{
 "code": "TS1165",
"nom": "Saouaf ",
"value": 3593.7 
},
{
 "code": "TS1170",
"nom": "Bizerte Nord  ",
"value":  14400 
},
{
 "code": "TS1171",
"nom": "Zarzouna ",
"value":  16472 
},
{
 "code": "TS1172",
"nom": "Bizerte Sud ",
"value":  10420 
},
{
 "code": "TS1173",
"nom": "Sedjnane ",
"value": 1517.5 
},
{
 "code": "TS1174",
"nom": "Djoumine ",
"value": 4256.5 
},
{
 "code": "TS1175",
"nom": "Mateur ",
"value": 7578.8 
},
{
 "code": "TS1176",
"nom": "Ghezala ",
"value": 4008.9 
},
{
 "code": "TS1177",
"nom": "Menzel Bourguiba ",
"value":  16130 
},
{
 "code": "TS1178",
"nom": "Tinja ",
"value":  13351 
},
{
 "code": "TS1179",
"nom": "Utique ",
"value":  41824 
},
{
 "code": "TS117A",
"nom": "Ghar El Meleh ",
"value":  16014 
},
{
 "code": "TS117B",
"nom": "Menzel Djemil ",
"value":  16265 
},
{
 "code": "TS117C",
"nom": "El Alia ",
"value":  17946 
},
{
 "code": "TS117D",
"nom": "Ras Djebel ",
"value":  11408 
},
{
 "code": "TS1210",
"nom": "Béja Nord  ",
"value": 6184.5 
},
{
 "code": "TS1211",
"nom": "Béja Sud ",
"value": 6491.3 
},
{
 "code": "TS1212",
"nom": "Amdoun ",
"value": 6492.2 
},
{
 "code": "TS1213",
"nom": "Nefza ",
"value": 3362.9 
},
{
 "code": "TS1214",
"nom": "Teboursouk ",
"value": 3591.7 
},
{
 "code": "TS1215",
"nom": "Tibar ",
"value": 5606.2 
},
{
 "code": "TS1216",
"nom": "Testour ",
"value": 3659.1 
},
{
 "code": "TS1217",
"nom": "Goubellat ",
"value": 2971.6 
},
{
 "code": "TS1218",
"nom": "Medjez El Bab ",
"value": 5053.3 
},
{
 "code": "TS1220",
"nom": "Jendouba  ",
"value": 9843.8 
},
{
 "code": "TS1221",
"nom": "Jendouba Nord ",
"value": 9338.5 
},
{
 "code": "TS1222",
"nom": "Bou Salem ",
"value": 8149.5 
},
{
 "code": "TS1223",
"nom": "Tabarka ",
"value": 3981.8 
},
{
 "code": "TS1224",
"nom": "Ain Draham ",
"value": 4371.8 
},
{
 "code": "TS1225",
"nom": "Fernana ",
"value": 5687.3 
},
{
 "code": "TS1226",
"nom": "Ghardimaou ",
"value": 1610.4 
},
{
 "code": "TS1227",
"nom": "Oued Meliz ",
"value": 5831.7 
},
{
 "code": "TS1228",
"nom": "Balta - Bou Aouane ",
"value": 6592.2 
},
{
 "code": "TS1230",
"nom": "Kef Ouest  ",
"value": 5520.6 
},
{
 "code": "TS1231",
"nom": "Kef Est ",
"value": 6066.3 
},
{
 "code": "TS1232",
"nom": "Nebeur ",
"value": 8296.6 
},
{
 "code": "TS1233",
"nom": "Sakiet Sidi Youssef ",
"value": 2744.5 
},
{
 "code": "TS1234",
"nom": "Tajerouine ",
"value":   3600 
},
{
 "code": "TS1235",
"nom": "Kalâat Snan ",
"value": 1441.1 
},
{
 "code": "TS1236",
"nom": "Kalâat Khasbah ",
"value": 1912.4 
},
{
 "code": "TS1237",
"nom": "Djerissa ",
"value": 2418.9 
},
{
 "code": "TS1238",
"nom": "El Ksour ",
"value": 1931.6 
},
{
 "code": "TS1239",
"nom": "Dahmani ",
"value": 3535.8 
},
{
 "code": "TS123A",
"nom": "Es-Sers ",
"value": 4280.1 
},
{
 "code": "TS1240",
"nom": "Siliana Nord  ",
"value": 4065.6 
},
{
 "code": "TS1241",
"nom": "Siliana Sud ",
"value": 3693.5 
},
{
 "code": "TS1242",
"nom": "Bou Arada ",
"value": 1992.3 
},
{
 "code": "TS1243",
"nom": "Gaâfour ",
"value": 2614.6 
},
{
 "code": "TS1244",
"nom": "El Krib ",
"value":   3545 
},
{
 "code": "TS1245",
"nom": "Bourouis ",
"value": 3801.2 
},
{
 "code": "TS1246",
"nom": "Makthar ",
"value": 2476.6 
},
{
 "code": "TS1247",
"nom": "Er-Rouhia ",
"value": 1790.2 
},
{
 "code": "TS1248",
"nom": "Kesra ",
"value": 2052.2 
},
{
 "code": "TS1249",
"nom": "Bargou ",
"value": 1727.3 
},
{
 "code": "TS124A",
"nom": "El Aroussa ",
"value":   1990 
},
{
 "code": "TS2110",
"nom": "Sousse Medina  ",
"value":  64883 
},
{
 "code": "TS2111",
"nom": "Sousse Riadh ",
"value":  67629 
},
{
 "code": "TS2112",
"nom": "Sousse Jawhara ",
"value":  68105 
},
{
 "code": "TS2113",
"nom": "Sousse Sidi Abdelhamid ",
"value":  63798 
},
{
 "code": "TS2114",
"nom": "Hammam Sousse ",
"value":  57664 
},
{
 "code": "TS2115",
"nom": "Akouda ",
"value":  42908 
},
{
 "code": "TS2116",
"nom": "Kalaâ Kebira ",
"value":  33510 
},
{
 "code": "TS2117",
"nom": "Sidi Bou Ali ",
"value":  17998 
},
{
 "code": "TS2118",
"nom": "Hergla ",
"value":  11560 
},
{
 "code": "TS2119",
"nom": "Enfidha ",
"value": 3718.3 
},
{
 "code": "TS211A",
"nom": "Bouficha ",
"value": 6681.7 
},
{
 "code": "TS211B",
"nom": "Kondar ",
"value": 7288.5 
},
{
 "code": "TS211C",
"nom": "Sidi El Héni ",
"value":  16871 
},
{
 "code": "TS211D",
"nom": "M saken ",
"value":  43727 
},
{
 "code": "TS211E",
"nom": "Kalaâ Seghira ",
"value":  48041 
},
{
 "code": "TS2120",
"nom": "Monastir  ",
"value":  59048 
},
{
 "code": "TS2121",
"nom": "Ouerdanine ",
"value":  66593 
},
{
 "code": "TS2122",
"nom": "Sahline ",
"value":  68493 
},
{
 "code": "TS2123",
"nom": "Zermadine ",
"value":  25353 
},
{
 "code": "TS2124",
"nom": "Beni Hassen ",
"value":  27639 
},
{
 "code": "TS2125",
"nom": "Jammel ",
"value":  50346 
},
{
 "code": "TS2126",
"nom": "Bembla ",
"value":  57893 
},
{
 "code": "TS2127",
"nom": "Moknine ",
"value":  27462 
},
{
 "code": "TS2128",
"nom": "Bekalta ",
"value":  19758 
},
{
 "code": "TS2129",
"nom": "Teboulba ",
"value":  25471 
},
{
 "code": "TS212A",
"nom": "Ksar Helal ",
"value":  36438 
},
{
 "code": "TS212B",
"nom": "Ksibet El Mediouni ",
"value":  43874 
},
{
 "code": "TS212C",
"nom": "Sayada-Lamta Bou-Hjar ",
"value":  35813 
},
{
 "code": "TS2130",
"nom": "Mahdia  ",
"value":  17294 
},
{
 "code": "TS2131",
"nom": "Bou Merdès ",
"value":  10014 
},
{
 "code": "TS2132",
"nom": "Ouled Chamekh ",
"value": 4448.3 
},
{
 "code": "TS2133",
"nom": "Chorbane ",
"value": 1462.7 
},
{
 "code": "TS2134",
"nom": "Hebira ",
"value": 1442.9 
},
{
 "code": "TS2135",
"nom": "Essouassi ",
"value": 2860.5 
},
{
 "code": "TS2136",
"nom": "El Djem ",
"value": 4456.2 
},
{
 "code": "TS2137",
"nom": "Chebba ",
"value": 3626.1 
},
{
 "code": "TS2138",
"nom": "Melloulech ",
"value": 3759.1 
},
{
 "code": "TS2139",
"nom": "Sidi Alouane ",
"value": 6402.5 
},
{
 "code": "TS213A",
"nom": "Ksour Essef ",
"value": 9464.9 
},
{
 "code": "TS2140",
"nom": "Sfax Ville  ",
"value":  64916 
},
{
 "code": "TS2141",
"nom": "Sfax Ouest ",
"value":  64013 
},
{
 "code": "TS2142",
"nom": "Sakiet Ezzit ",
"value":  56932 
},
{
 "code": "TS2143",
"nom": "Sakiet Eddaïer ",
"value":  60968 
},
{
 "code": "TS2144",
"nom": "Sfax Sud ",
"value":  62641 
},
{
 "code": "TS2145",
"nom": "Tina ",
"value":  56042 
},
{
 "code": "TS2146",
"nom": "Agareb ",
"value":  16796 
},
{
 "code": "TS2147",
"nom": "Djebeniana ",
"value": 7260.6 
},
{
 "code": "TS2148",
"nom": "El Amra ",
"value":  33209 
},
{
 "code": "TS2149",
"nom": "El Hencha ",
"value": 5494.3 
},
{
 "code": "TS214A",
"nom": "Menzel Chaker ",
"value": 1741.8 
},
{
 "code": "TS214B",
"nom": "Ghraiba ",
"value": 1174.9 
},
{
 "code": "TS214C",
"nom": "Bir ali Ben Kelifa ",
"value": 1297.6 
},
{
 "code": "TS214D",
"nom": "Skhira ",
"value":  963.7 
},
{
 "code": "TS214E",
"nom": "Mahres ",
"value": 4651.5 
},
{
 "code": "TS214F",
"nom": "Kerkenah ",
"value": 1437.5 
},
{
 "code": "TS2210",
"nom": "Kairouan Nord  ",
"value": 9067.8 
},
{
 "code": "TS2211",
"nom": "Kairouan Sud ",
"value": 9623.5 
},
{
 "code": "TS2212",
"nom": "Echebika ",
"value": 6048.2 
},
{
 "code": "TS2213",
"nom": "Sbikha ",
"value": 2897.5 
},
{
 "code": "TS2214",
"nom": "EL Ouslatia ",
"value": 1152.2 
},
{
 "code": "TS2215",
"nom": "Haffouz ",
"value": 1639.5 
},
{
 "code": "TS2216",
"nom": "El Alâa ",
"value": 1329.9 
},
{
 "code": "TS2217",
"nom": "Hajeb el Ayoun ",
"value": 1677.5 
},
{
 "code": "TS2218",
"nom": "Nasrallah ",
"value": 1106.6 
},
{
 "code": "TS2219",
"nom": "Echrarda ",
"value":  908.2 
},
{
 "code": "TS221A",
"nom": "Bouhajla ",
"value": 2800.7 
},
{
 "code": "TS2220",
"nom": "Kasserine Nord  ",
"value": 5502.9 
},
{
 "code": "TS2221",
"nom": "Kasserine Sud ",
"value": 5128.5 
},
{
 "code": "TS2222",
"nom": "Ezzouhour ",
"value": 5457.6 
},
{
 "code": "TS2223",
"nom": "Hassi Ferid ",
"value": 1292.2 
},
{
 "code": "TS2224",
"nom": "Sbeitla ",
"value": 2390.2 
},
{
 "code": "TS2225",
"nom": "Sbiba ",
"value": 1817.8 
},
{
 "code": "TS2226",
"nom": "Djedeliane ",
"value": 1443.5 
},
{
 "code": "TS2227",
"nom": "El Ayoun ",
"value": 1413.2 
},
{
 "code": "TS2228",
"nom": "Thala ",
"value": 1562.4 
},
{
 "code": "TS2229",
"nom": "Hidra ",
"value":   1319 
},
{
 "code": "TS222A",
"nom": "Foussana ",
"value": 1898.9 
},
{
 "code": "TS222B",
"nom": "Feriana ",
"value": 1439.2 
},
{
 "code": "TS222C",
"nom": "Majel Bel Abbès ",
"value": 872.53 
},
{
 "code": "TS2230",
"nom": "Sidi Bouzid Ouest  ",
"value": 4836.1 
},
{
 "code": "TS2231",
"nom": "Sidi Bouzid Est ",
"value": 3596.1 
},
{
 "code": "TS2232",
"nom": "Jilma ",
"value": 1595.6 
},
{
 "code": "TS2233",
"nom": "Cebalet Ouled Asker ",
"value": 2398.4 
},
{
 "code": "TS2234",
"nom": "Bir El Hafey ",
"value": 3306.6 
},
{
 "code": "TS2235",
"nom": "Sidi Ali Ben Aoûn ",
"value": 1049.3 
},
{
 "code": "TS2236",
"nom": "Menzel Bouzaïenne ",
"value": 963.75 
},
{
 "code": "TS2237",
"nom": "Meknassy ",
"value": 1194.5 
},
{
 "code": "TS2238",
"nom": "Souk Jedid ",
"value": 2312.7 
},
{
 "code": "TS2239",
"nom": "Mezzouna ",
"value": 955.38 
},
{
 "code": "TS223A",
"nom": "Regueb ",
"value": 1658.2 
},
{
 "code": "TS223B",
"nom": "Ouled Haffouz ",
"value": 1353.1 
},
{
 "code": "TS3110",
"nom": "Gabes Medina  ",
"value":  16759 
},
{
 "code": "TS3111",
"nom": "Gabes Ouest ",
"value":  17521 
},
{
 "code": "TS3112",
"nom": "Gabes Sud ",
"value":  17004 
},
{
 "code": "TS3113",
"nom": "Ghanouch ",
"value":  16114 
},
{
 "code": "TS3114",
"nom": "El Metouia ",
"value": 7812.8 
},
{
 "code": "TS3115",
"nom": "Menzel El Habib ",
"value": 584.48 
},
{
 "code": "TS3116",
"nom": "El Hamma ",
"value": 1816.3 
},
{
 "code": "TS3117",
"nom": "Matmata ",
"value": 681.21 
},
{
 "code": "TS3118",
"nom": "Nouvelle Matmata ",
"value":   5562 
},
{
 "code": "TS3119",
"nom": "Mareth ",
"value": 4235.8 
},
{
 "code": "TS3120",
"nom": "Medenine Nord  ",
"value": 6586.1 
},
{
 "code": "TS3121",
"nom": "Medenine Sud ",
"value": 4412.8 
},
{
 "code": "TS3122",
"nom": "Beni Khedech ",
"value": 1623.1 
},
{
 "code": "TS3123",
"nom": "Ben Guerdane ",
"value": 3126.8 
},
{
 "code": "TS3124",
"nom": "Zarzis ",
"value": 4054.3 
},
{
 "code": "TS3125",
"nom": "Djerba Houmet Souk ",
"value":  10990 
},
{
 "code": "TS3126",
"nom": "Djerba Midoun ",
"value":  11064 
},
{
 "code": "TS3127",
"nom": "Djerba Ajim ",
"value":  10247 
},
{
 "code": "TS3128",
"nom": "Sidi Makhloulf ",
"value": 4042.2 
},
{
 "code": "TS3130",
"nom": "Tataouine Nord  ",
"value": 3547.4 
},
{
 "code": "TS3131",
"nom": "Tataouine Sud ",
"value": 1922.9 
},
{
 "code": "TS3132",
"nom": "Smâr ",
"value": 1956.8 
},
{
 "code": "TS3133",
"nom": "Bir Lahmar ",
"value": 3286.1 
},
{
 "code": "TS3134",
"nom": "Ghomrassen ",
"value": 1768.1 
},
{
 "code": "TS3135",
"nom": "Dhehiba ",
"value":    296 
},
{
 "code": "TS3136",
"nom": "Remada ",
"value":    595 
},
{
 "code": "TS3210",
"nom": "Gafsa Nord  ",
"value": 2695.8 
},
{
 "code": "TS3211",
"nom": "Sidi Aïch ",
"value": 2403.7 
},
{
 "code": "TS3212",
"nom": "El Ksar ",
"value": 6058.6 
},
{
 "code": "TS3213",
"nom": "Gafsa Sud ",
"value": 8006.6 
},
{
 "code": "TS3214",
"nom": "Oum El Araies ",
"value": 1825.5 
},
{
 "code": "TS3215",
"nom": "Redeyef ",
"value": 1256.8 
},
{
 "code": "TS3216",
"nom": "Metlaoui ",
"value": 2676.4 
},
{
 "code": "TS3217",
"nom": "Mdhila ",
"value": 2315.5 
},
{
 "code": "TS3218",
"nom": "EL Guetar ",
"value": 1771.6 
},
{
 "code": "TS3219",
"nom": "Belkhir ",
"value":  470.6 
},
{
 "code": "TS321A",
"nom": "Sned ",
"value": 1254.8 
},
{
 "code": "TS3220",
"nom": "Tozeur  ",
"value": 2893.7 
},
{
 "code": "TS3221",
"nom": "Degach ",
"value": 2022.4 
},
{
 "code": "TS3222",
"nom": "Tameghza ",
"value": 412.96 
},
{
 "code": "TS3223",
"nom": "Nefta ",
"value": 2023.5 
},
{
 "code": "TS3224",
"nom": "Hazoua ",
"value": 722.04 
},
{
 "code": "TS3230",
"nom": "Kebili Sud  ",
"value": 2836.6 
},
{
 "code": "TS3231",
"nom": "Kebeli Nord ",
"value": 2990.9 
},
{
 "code": "TS3232",
"nom": "Souk El Ahed ",
"value": 677.14 
},
{
 "code": "TS3233",
"nom": "Douz Nord ",
"value": 1193.4 
},
{
 "code": "TS3234",
"nom": "Douz Sud ",
"value": 709.05 
},
{
 "code": "TS3235",
"nom": "Faouar ",
"value":    643 
} 
]
