[
 {
 "from":      0,
"to":      0,
"color": "#64110F" 
},
{
 "from":      0,
"to":      0,
"color": "#8F1E21" 
},
{
 "from":      0,
"to":      0,
"color": "#BA2C33" 
},
{
 "from":      0,
"to":      0,
"color": "#CB464C" 
},
{
 "from":      0,
"to": 2591.5,
"color": "#D56268" 
},
{
 "from": 2591.5,
"to": 4107.1,
"color": "#DE7C81" 
},
{
 "from": 4107.1,
"to": 4498.7,
"color": "#E59296" 
},
{
 "from": 4498.7,
"to": 5204.1,
"color": "#ECA7AB" 
},
{
 "from": 5204.1,
"to":   7680,
"color": "#F4BDC0" 
} 
]
