[
 {
 "from":  10752,
"to": 1.1111e+13,
"color": "#64110F" 
},
{
 "from": 1.1111e+13,
"to": 2.2222e+13,
"color": "#8F1E21" 
},
{
 "from": 2.2222e+13,
"to": 3.3333e+13,
"color": "#BA2C33" 
},
{
 "from": 3.3333e+13,
"to": 4.4444e+13,
"color": "#CB464C" 
},
{
 "from": 4.4444e+13,
"to": 5.5556e+13,
"color": "#D56268" 
},
{
 "from": 5.5556e+13,
"to": 6.6667e+13,
"color": "#DE7C81" 
},
{
 "from": 6.6667e+13,
"to": 7.7778e+13,
"color": "#E59296" 
},
{
 "from": 7.7778e+13,
"to": 8.8889e+13,
"color": "#ECA7AB" 
},
{
 "from": 8.8889e+13,
"to":  1e+14,
"color": "#F4BDC0" 
} 
]
